rw_scheduler/__init__.py
rw_scheduler/mysql_basic.py
rw_scheduler-0.0.3.8.dist-info/METADATA
rw_scheduler-0.0.3.8.dist-info/WHEEL
rw_scheduler-0.0.3.8.dist-info/top_level.txt
rw_scheduler-0.0.3.8.dist-info/RECORD
