Metadata-Version: 2.1
Name: rw-scheduler
Version: 0.0.3.8
Summary: Wrapper around apscheduler
Home-page: https://github.com/Raevsky-Team/planfact_api
Author: Mihail Granovskij
Author-email: mihail.granovskij@gmail.com
License: UNKNOWN
Project-URL: Bug Tracker, https://github.com/Raevsky-Team/planfact_api/issues
Platform: UNKNOWN
Classifier: Programming Language :: Python :: 3
Classifier: License :: OSI Approved :: MIT License
Classifier: Operating System :: OS Independent
Requires-Python: >=3.9
Requires-Dist: mysql-connector
Requires-Dist: apscheduler
Requires-Dist: pydantic
Requires-Dist: python-telegram-bot
